filename_templates/__init__.py
filename_templates/filenames.py
filename_templates-1.3.dist-info/licenses/LICENSE
filename_templates-1.3.dist-info/METADATA
filename_templates-1.3.dist-info/WHEEL
filename_templates-1.3.dist-info/top_level.txt
filename_templates-1.3.dist-info/RECORD
