Metadata-Version: 2.4
Name: filename-templates
Version: 1.3
Summary: Make filenames from string templates
Author-email: Marijn van Vliet <w.m.vanvliet@gmail.com>
License: BSD-3-Clause
Project-URL: Bug Tracker, https://github.com/wmvanvliet/filename-templates/issues/
Project-URL: Source Code, https://github.com/wmvanvliet/filename-templates
Project-URL: Homepage, https://github.com/wmvanvliet/filename-templates
Keywords: string,pathlib,template
Classifier: Intended Audience :: Science/Research
Classifier: Intended Audience :: Developers
Classifier: License :: OSI Approved
Classifier: Programming Language :: Python
Classifier: Topic :: Software Development
Classifier: Topic :: Scientific/Engineering
Classifier: Operating System :: Microsoft :: Windows
Classifier: Operating System :: POSIX
Classifier: Operating System :: Unix
Classifier: Operating System :: MacOS
Requires-Python: >=3.5
License-File: LICENSE
Dynamic: license-file
